pyduke_energy/__init__.py
pyduke_energy/client.py
pyduke_energy/const.py
pyduke_energy/errors.py
pyduke_energy/realtime.py
pyduke_energy/types.py
pyduke_energy/utils.py
pyduke_energy-1.0.6.dist-info/LICENSE
pyduke_energy-1.0.6.dist-info/METADATA
pyduke_energy-1.0.6.dist-info/WHEEL
pyduke_energy-1.0.6.dist-info/top_level.txt
pyduke_energy-1.0.6.dist-info/RECORD
