Metadata-Version: 2.1
Name: pyduke-energy
Version: 1.0.6
Summary: Python Wrapper for unofficial Duke Energy REST API
Home-page: https://github.com/mjmeli/pyduke-energy
Author: Michael Meli
Author-email: mjmeli94@gmail.com
Project-URL: Bug Tracker, https://github.com/mjmeli/pyduke-energy/issues
Classifier: Programming Language :: Python :: 3
Classifier: License :: OSI Approved :: MIT License
Classifier: Operating System :: OS Independent
Classifier: Development Status :: 3 - Alpha
Requires-Python: >=3.7
License-File: LICENSE
Requires-Dist: aiohttp
Requires-Dist: python-dateutil
Requires-Dist: paho-mqtt
Provides-Extra: example
Requires-Dist: jsonpickle ; extra == 'example'
Requires-Dist: kafka-python ; extra == 'example'
Provides-Extra: release
Requires-Dist: build ; extra == 'release'
Requires-Dist: twine ; extra == 'release'
Provides-Extra: test
Requires-Dist: tox ; extra == 'test'
Requires-Dist: pytest (<7.3.0,>=7.1.1) ; extra == 'test'
Requires-Dist: pytest-asyncio (<0.21.0,>=0.18.3) ; extra == 'test'
Requires-Dist: pytest-cov (<4.1,>=3.0) ; extra == 'test'
Requires-Dist: pytest-timeout (~=2.1.0) ; extra == 'test'
Requires-Dist: black (==22.12.0) ; extra == 'test'
Requires-Dist: flake8 (==5.0.4) ; extra == 'test'
Requires-Dist: pylint (==2.15.9) ; extra == 'test'
Requires-Dist: pydocstyle (==6.1.1) ; extra == 'test'
Requires-Dist: isort (~=5.10.1) ; extra == 'test'
